MarkdownYufaShuoming/README.md
MarkdownYufaShuoming/__init__.py
MarkdownYufaShuoming/__main__.py
MarkdownYufaShuoming/file.epub
MarkdownYufaShuoming/index.html
MarkdownYufaShuoming/css/__init__.py
MarkdownYufaShuoming/css/annotations.css
MarkdownYufaShuoming/css/main.css
MarkdownYufaShuoming/css/normalize.css
MarkdownYufaShuoming/css/popup.css
MarkdownYufaShuoming/font/__init__.py
MarkdownYufaShuoming/font/fontello.eot
MarkdownYufaShuoming/font/fontello.svg
MarkdownYufaShuoming/font/fontello.ttf
MarkdownYufaShuoming/font/fontello.woff
MarkdownYufaShuoming/img/__init__.py
MarkdownYufaShuoming/img/annotator-glyph-sprite.png
MarkdownYufaShuoming/img/annotator-icon-sprite.png
MarkdownYufaShuoming/img/apple-touch-icon.png
MarkdownYufaShuoming/img/cancelfullscreen.png
MarkdownYufaShuoming/img/close.png
MarkdownYufaShuoming/img/fullscreen.png
MarkdownYufaShuoming/img/loader.gif
MarkdownYufaShuoming/img/menu-icon.png
MarkdownYufaShuoming/img/save.png
MarkdownYufaShuoming/img/saved.png
MarkdownYufaShuoming/img/settings-s.png
MarkdownYufaShuoming/img/settings.png
MarkdownYufaShuoming/img/star.png
MarkdownYufaShuoming/js/__init__.py
MarkdownYufaShuoming/js/epub.js
MarkdownYufaShuoming/js/epub.min.js
MarkdownYufaShuoming/js/epub.min.map
MarkdownYufaShuoming/js/hooks.min.js
MarkdownYufaShuoming/js/hooks.min.map
MarkdownYufaShuoming/js/reader.js
MarkdownYufaShuoming/js/reader.js.map
MarkdownYufaShuoming/js/reader.min.js
MarkdownYufaShuoming/js/reader.min.map
MarkdownYufaShuoming/js/hooks/__init__.py
MarkdownYufaShuoming/js/hooks/extensions/__init__.py
MarkdownYufaShuoming/js/hooks/extensions/highlight.js
MarkdownYufaShuoming/js/libs/__init__.py
MarkdownYufaShuoming/js/libs/jquery.min.js
MarkdownYufaShuoming/js/libs/localforage.min.js
MarkdownYufaShuoming/js/libs/screenfull.js
MarkdownYufaShuoming/js/libs/screenfull.min.js
MarkdownYufaShuoming/js/libs/zip.min.js
MarkdownYufaShuoming/js/plugins/__init__.py
MarkdownYufaShuoming/js/plugins/hypothesis.js
markdown_yufa_shuoming-2024.3.2.0.dist-info/METADATA
markdown_yufa_shuoming-2024.3.2.0.dist-info/WHEEL
markdown_yufa_shuoming-2024.3.2.0.dist-info/entry_points.txt
markdown_yufa_shuoming-2024.3.2.0.dist-info/top_level.txt
markdown_yufa_shuoming-2024.3.2.0.dist-info/RECORD
